netpin2excel/__init__.py
netpin2excel/netpin_process.pyd
netpin2excel-0.2.0.dist-info/METADATA
netpin2excel-0.2.0.dist-info/WHEEL
netpin2excel-0.2.0.dist-info/top_level.txt
netpin2excel-0.2.0.dist-info/RECORD
