Metadata-Version: 2.1
Name: netpin2excel
Version: 0.2.0
Summary: A sample Python package with a .pyd file
Home-page: https://github.com/yourusername/my_package
Author: hfh
Author-email: your.email@example.com
Classifier: Programming Language :: Python :: 3
Classifier: License :: OSI Approved :: MIT License
Classifier: Operating System :: OS Independent
Requires-Python: >=3.6
